Metadata-Version: 1.0
Name: tiandafu-distributions
Version: 1.0
Summary: Gaussian distributions
Home-page: UNKNOWN
Author: Dafu Tian
Author-email: weiyiwdeng@gmail.com
License: UNKNOWN
Platform: UNKNOWN
